[
 {
  "sid":"THEOV:343:257:229",
  "className":"Simulink.Outport",
  "icon":"WebViewIcon3",
  "name":"ug,vg,wg",
  "label":"ug,vg,wg",
  "parent":"THEOV:343:257:203",
  "inspector":{
   "params":[
    "Port",
    "IconDisplay",
    "OutMin",
    "OutMax",
    "OutDataTypeStr",
    "LockScale",
    "Unit",
    "PortDimensions",
    "VarSizeSig",
    "SampleTime",
    "SignalType",
    "BusOutputAsStruct",
    "EnsureOutportIsVirtual",
    "InitialOutput",
    "MustResolveToSignalObject",
    "OutputWhenDisabled",
    "OutputWhenUnConnected",
    "OutputWhenUnconnectedValue",
    "SignalName",
    "SignalObject",
    "SourceOfInitialOutputValue",
    "StorageClass",
    "VectorParamsAs1DForOutWhenUnconnected"
   ],
   "values":[
    "1",
    "Port number",
    "[]",
    "[]",
    "Inherit: auto",
    "off",
    "inherit",
    "-1",
    "Inherit",
    "-1",
    "auto",
    "off",
    "off",
    "[]",
    "off",
    "held",
    "off",
    "0",
    "",
    [
    ],
    "Dialog",
    "Auto",
    "off"
   ],
   "tabs":[
    "Main",
    "Signal Attributes",
    "-Other"
   ],
   "tabs_idx":[
    0,
    2,
    11
   ]
  },
  "viewer":{
   "jshandler":"webview/handlers/ElementHandler"
  },
  "obj_viewer":[
  ],
  "finder":{
   "blocktype":"Outport",
   "masktype":""
  }
 },
 {
  "sid":"THEOV:343:257:212",
  "className":"Simulink.SubSystem",
  "icon":"WebViewIcon2",
  "name":"convert to earth coords",
  "label":"convert to earth coords",
  "parent":"THEOV:343:257:203",
  "inspector":{
   "params":[
    "ShowPortLabels",
    "Permissions",
    "ErrorFcn",
    "PermitHierarchicalResolution",
    "TreatAsAtomicUnit",
    "TreatAsGroupedWhenPropagatingVariantConditions",
    "RTWSystemCode",
    "ActiveVariant",
    "ActiveVariantBlock",
    "AllowZeroVariantControls",
    "BlockChoice",
    "FunctionInterfaceSpec",
    "FunctionWithSeparateData",
    "GeneratePreprocessorConditionals",
    "IsSubsystemVirtual",
    "LabelModeActiveChoice",
    "MemberBlocks",
    "MinAlgLoopOccurrences",
    "PropExecContextOutsideSubsystem",
    "PropagateVariantConditions",
    "RTWFcnName",
    "RTWFcnNameOpts",
    "RTWFileName",
    "RTWFileNameOpts",
    "RTWMemSecDataConstants",
    "RTWMemSecDataInternal",
    "RTWMemSecDataParameters",
    "RTWMemSecFuncExecute",
    "RTWMemSecFuncInitTerm",
    "SystemSampleTime",
    "TemplateBlock",
    "Variant",
    "VariantControl",
    "VariantControlMode"
   ],
   "values":[
    "FromPortIcon",
    "ReadWrite",
    "",
    "All",
    "off",
    "on",
    "Auto",
    "",
    "",
    "off",
    "",
    "void_void",
    "off",
    "off",
    "on",
    "",
    "",
    "off",
    "off",
    "off",
    "",
    "Auto",
    "",
    "Auto",
    "Inherit from model",
    "Inherit from model",
    "Inherit from model",
    "Inherit from model",
    "Inherit from model",
    "-1",
    "",
    "off",
    "",
    "Expression"
   ],
   "tabs":[
    "Main",
    "Code Generation",
    "-Other"
   ],
   "tabs_idx":[
    0,
    6,
    7
   ]
  },
  "viewer":{
   "jshandler":"webview/handlers/ContainerHandler"
  },
  "obj_viewer":[
  ],
  "finder":{
   "blocktype":"SubSystem",
   "masktype":""
  }
 },
 {
  "sid":"THEOV:343:257:211",
  "className":"Simulink.Concatenate",
  "icon":"WebViewIcon3",
  "name":"Vector Concatenate",
  "label":"Vector Concatenate",
  "parent":"THEOV:343:257:203",
  "inspector":{
   "params":[
    "NumInputs",
    "Mode",
    "ConcatenateDimension"
   ],
   "values":[
    "3",
    "Vector",
    "1"
   ],
   "tabs":[
    "Parameter Attributes",
    "-Other"
   ],
   "tabs_idx":[
    0,
    2
   ]
  },
  "viewer":{
   "jshandler":"webview/handlers/ElementHandler"
  },
  "obj_viewer":[
  ],
  "finder":{
   "blocktype":"Concatenate",
   "masktype":""
  }
 },
 {
  "sid":"THEOV:343:257:210",
  "className":"Simulink.Reshape",
  "icon":"WebViewIcon3",
  "name":"Reshape1",
  "label":"Reshape1",
  "parent":"THEOV:343:257:203",
  "inspector":{
   "params":[
    "OutputDimensionality",
    "OutputDimensions"
   ],
   "values":[
    "1-D array",
    "[1,1]"
   ],
   "tabs":[
    "Parameter Attributes"
   ],
   "tabs_idx":0
  },
  "viewer":{
   "jshandler":"webview/handlers/ElementHandler"
  },
  "obj_viewer":[
  ],
  "finder":{
   "blocktype":"Reshape",
   "masktype":""
  }
 },
 {
  "sid":"THEOV:343:257:209",
  "className":"Simulink.Reshape",
  "icon":"WebViewIcon3",
  "name":"Reshape",
  "label":"Reshape",
  "parent":"THEOV:343:257:203",
  "inspector":{
   "params":[
    "OutputDimensionality",
    "OutputDimensions"
   ],
   "values":[
    "Customize",
    "[3,1]"
   ],
   "tabs":[
    "Parameter Attributes"
   ],
   "tabs_idx":0
  },
  "viewer":{
   "jshandler":"webview/handlers/ElementHandler"
  },
  "obj_viewer":[
  ],
  "finder":{
   "blocktype":"Reshape",
   "masktype":""
  }
 },
 {
  "sid":"THEOV:343:257:208",
  "className":"Simulink.Product",
  "icon":"WebViewIcon3",
  "name":"Product",
  "label":"Product",
  "parent":"THEOV:343:257:203",
  "inspector":{
   "params":[
    "Inputs",
    "Multiplication",
    "InputSameDT",
    "OutMin",
    "OutMax",
    "OutDataTypeStr",
    "LockScale",
    "RndMeth",
    "SaturateOnIntegerOverflow",
    "CollapseDim",
    "CollapseMode",
    "SampleTime"
   ],
   "values":[
    "2",
    "Matrix(*)",
    "off",
    "[]",
    "[]",
    "Inherit: Same as first input",
    "off",
    "Floor",
    "on",
    "1",
    "All dimensions",
    "-1"
   ],
   "tabs":[
    "Main",
    "Signal Attributes",
    "-Other"
   ],
   "tabs_idx":[
    0,
    2,
    9
   ]
  },
  "viewer":{
   "jshandler":"webview/handlers/ElementHandler"
  },
  "obj_viewer":[
  ],
  "finder":{
   "blocktype":"Product",
   "masktype":""
  }
 },
 {
  "sid":"THEOV:343:257:207",
  "className":"Simulink.Demux",
  "icon":"WebViewIcon3",
  "name":"Demux",
  "label":"Demux",
  "parent":"THEOV:343:257:203",
  "inspector":{
   "params":[
    "Outputs",
    "DisplayOption",
    "BusSelectionMode"
   ],
   "values":[
    "3",
    "none",
    "off"
   ],
   "tabs":[
    "Parameter Attributes"
   ],
   "tabs_idx":0
  },
  "viewer":{
   "jshandler":"webview/handlers/ElementHandler"
  },
  "obj_viewer":[
  ],
  "finder":{
   "blocktype":"Demux",
   "masktype":""
  }
 },
 {
  "sid":"THEOV:343:257:206",
  "className":"Simulink.Inport",
  "icon":"WebViewIcon3",
  "name":"ug_l,vg_l,wg_l",
  "label":"ug_l,vg_l,wg_l",
  "parent":"THEOV:343:257:203",
  "inspector":{
   "params":[
    "Port",
    "IconDisplay",
    "LatchByDelayingOutsideSignal",
    "LatchInputForFeedbackSignals",
    "OutputFunctionCall",
    "OutMin",
    "OutMax",
    "OutDataTypeStr",
    "LockScale",
    "Unit",
    "PortDimensions",
    "VarSizeSig",
    "SampleTime",
    "SignalType",
    "BusOutputAsStruct",
    "InputConnect",
    "Interpolate"
   ],
   "values":[
    "3",
    "Port number",
    "off",
    "off",
    "off",
    "[]",
    "[]",
    "Inherit: auto",
    "off",
    "inherit",
    "-1",
    "Inherit",
    "-1",
    "auto",
    "off",
    "",
    "on"
   ],
   "tabs":[
    "Main",
    "Signal Attributes",
    "-Other"
   ],
   "tabs_idx":[
    0,
    4,
    14
   ]
  },
  "viewer":{
   "jshandler":"webview/handlers/ElementHandler"
  },
  "obj_viewer":[
  ],
  "finder":{
   "blocktype":"Inport",
   "masktype":""
  }
 },
 {
  "sid":"THEOV:343:257:205",
  "className":"Simulink.Inport",
  "icon":"WebViewIcon3",
  "name":"Wind direction",
  "label":"Wind direction",
  "parent":"THEOV:343:257:203",
  "inspector":{
   "params":[
    "Port",
    "IconDisplay",
    "LatchByDelayingOutsideSignal",
    "LatchInputForFeedbackSignals",
    "OutputFunctionCall",
    "OutMin",
    "OutMax",
    "OutDataTypeStr",
    "LockScale",
    "Unit",
    "PortDimensions",
    "VarSizeSig",
    "SampleTime",
    "SignalType",
    "BusOutputAsStruct",
    "InputConnect",
    "Interpolate"
   ],
   "values":[
    "2",
    "Port number",
    "off",
    "off",
    "off",
    "[]",
    "[]",
    "Inherit: auto",
    "off",
    "inherit",
    "-1",
    "Inherit",
    "-1",
    "auto",
    "off",
    "",
    "on"
   ],
   "tabs":[
    "Main",
    "Signal Attributes",
    "-Other"
   ],
   "tabs_idx":[
    0,
    4,
    14
   ]
  },
  "viewer":{
   "jshandler":"webview/handlers/ElementHandler"
  },
  "obj_viewer":[
  ],
  "finder":{
   "blocktype":"Inport",
   "masktype":""
  }
 },
 {
  "sid":"THEOV:343:257:204",
  "className":"Simulink.Inport",
  "icon":"WebViewIcon3",
  "name":"DCM",
  "label":"DCM",
  "parent":"THEOV:343:257:203",
  "inspector":{
   "params":[
    "Port",
    "IconDisplay",
    "LatchByDelayingOutsideSignal",
    "LatchInputForFeedbackSignals",
    "OutputFunctionCall",
    "OutMin",
    "OutMax",
    "OutDataTypeStr",
    "LockScale",
    "Unit",
    "PortDimensions",
    "VarSizeSig",
    "SampleTime",
    "SignalType",
    "BusOutputAsStruct",
    "InputConnect",
    "Interpolate"
   ],
   "values":[
    "1",
    "Port number",
    "off",
    "off",
    "off",
    "[]",
    "[]",
    "Inherit: auto",
    "off",
    "inherit",
    "-1",
    "Inherit",
    "-1",
    "auto",
    "off",
    "",
    "on"
   ],
   "tabs":[
    "Main",
    "Signal Attributes",
    "-Other"
   ],
   "tabs_idx":[
    0,
    4,
    14
   ]
  },
  "viewer":{
   "jshandler":"webview/handlers/ElementHandler"
  },
  "obj_viewer":[
  ],
  "finder":{
   "blocktype":"Inport",
   "masktype":""
  }
 },
 {
  "sid":"THEOV:343:257:210#out:1",
  "className":"Simulink.Line",
  "icon":"WebViewIcon5",
  "name":"",
  "label":"",
  "parent":"THEOV:343:257:203",
  "inspector":{
   "params":[
    "SignalNameFromLabel",
    "MustResolveToSignal",
    "ShowPropagatedSignal",
    "DataLogging",
    "TestPoint",
    "SignalObjectPackage",
    "StorageClass",
    "Description",
    "documentLink"
   ],
   "values":[
    "",
    "off",
    "off",
    "off",
    "off",
    "Simulink",
    "Auto",
    "",
    ""
   ],
   "tabs":[
    "Parameter Attributes",
    "Logging and Accessibility",
    "Code Generation",
    "Documentation"
   ],
   "tabs_idx":[
    0,
    3,
    5,
    7
   ]
  },
  "viewer":{
   "jshandler":"webview/handlers/ElementHandler"
  },
  "obj_viewer":[
  ],
  "finder":[
  ]
 },
 {
  "sid":"THEOV:343:257:209#out:1",
  "className":"Simulink.Line",
  "icon":"WebViewIcon5",
  "name":"",
  "label":"",
  "parent":"THEOV:343:257:203",
  "inspector":{
   "params":[
    "SignalNameFromLabel",
    "MustResolveToSignal",
    "ShowPropagatedSignal",
    "DataLogging",
    "TestPoint",
    "SignalObjectPackage",
    "StorageClass",
    "Description",
    "documentLink"
   ],
   "values":[
    "",
    "off",
    "off",
    "off",
    "off",
    "Simulink",
    "Auto",
    "",
    ""
   ],
   "tabs":[
    "Parameter Attributes",
    "Logging and Accessibility",
    "Code Generation",
    "Documentation"
   ],
   "tabs_idx":[
    0,
    3,
    5,
    7
   ]
  },
  "viewer":{
   "jshandler":"webview/handlers/ElementHandler"
  },
  "obj_viewer":[
  ],
  "finder":[
  ]
 },
 {
  "sid":"THEOV:343:257:206#out:1",
  "className":"Simulink.Line",
  "icon":"WebViewIcon5",
  "name":"",
  "label":"",
  "parent":"THEOV:343:257:203",
  "inspector":{
   "params":[
    "SignalNameFromLabel",
    "MustResolveToSignal",
    "ShowPropagatedSignal",
    "DataLogging",
    "TestPoint",
    "SignalObjectPackage",
    "StorageClass",
    "Description",
    "documentLink"
   ],
   "values":[
    "",
    "off",
    "off",
    "off",
    "off",
    "Simulink",
    "Auto",
    "",
    ""
   ],
   "tabs":[
    "Parameter Attributes",
    "Logging and Accessibility",
    "Code Generation",
    "Documentation"
   ],
   "tabs_idx":[
    0,
    3,
    5,
    7
   ]
  },
  "viewer":{
   "jshandler":"webview/handlers/ElementHandler"
  },
  "obj_viewer":[
  ],
  "finder":[
  ]
 },
 {
  "sid":"THEOV:343:257:208#out:1",
  "className":"Simulink.Line",
  "icon":"WebViewIcon5",
  "name":"",
  "label":"",
  "parent":"THEOV:343:257:203",
  "inspector":{
   "params":[
    "SignalNameFromLabel",
    "MustResolveToSignal",
    "ShowPropagatedSignal",
    "DataLogging",
    "TestPoint",
    "SignalObjectPackage",
    "StorageClass",
    "Description",
    "documentLink"
   ],
   "values":[
    "",
    "off",
    "off",
    "off",
    "off",
    "Simulink",
    "Auto",
    "",
    ""
   ],
   "tabs":[
    "Parameter Attributes",
    "Logging and Accessibility",
    "Code Generation",
    "Documentation"
   ],
   "tabs_idx":[
    0,
    3,
    5,
    7
   ]
  },
  "viewer":{
   "jshandler":"webview/handlers/ElementHandler"
  },
  "obj_viewer":[
  ],
  "finder":[
  ]
 },
 {
  "sid":"THEOV:343:257:207#out:3",
  "className":"Simulink.Line",
  "icon":"WebViewIcon5",
  "name":"",
  "label":"",
  "parent":"THEOV:343:257:203",
  "inspector":{
   "params":[
    "SignalNameFromLabel",
    "MustResolveToSignal",
    "ShowPropagatedSignal",
    "DataLogging",
    "TestPoint",
    "SignalObjectPackage",
    "StorageClass",
    "Description",
    "documentLink"
   ],
   "values":[
    "",
    "off",
    "off",
    "off",
    "off",
    "Simulink",
    "Auto",
    "",
    ""
   ],
   "tabs":[
    "Parameter Attributes",
    "Logging and Accessibility",
    "Code Generation",
    "Documentation"
   ],
   "tabs_idx":[
    0,
    3,
    5,
    7
   ]
  },
  "viewer":{
   "jshandler":"webview/handlers/ElementHandler"
  },
  "obj_viewer":[
  ],
  "finder":[
  ]
 },
 {
  "sid":"THEOV:343:257:207#out:2",
  "className":"Simulink.Line",
  "icon":"WebViewIcon5",
  "name":"",
  "label":"",
  "parent":"THEOV:343:257:203",
  "inspector":{
   "params":[
    "SignalNameFromLabel",
    "MustResolveToSignal",
    "ShowPropagatedSignal",
    "DataLogging",
    "TestPoint",
    "SignalObjectPackage",
    "StorageClass",
    "Description",
    "documentLink"
   ],
   "values":[
    "",
    "off",
    "off",
    "off",
    "off",
    "Simulink",
    "Auto",
    "",
    ""
   ],
   "tabs":[
    "Parameter Attributes",
    "Logging and Accessibility",
    "Code Generation",
    "Documentation"
   ],
   "tabs_idx":[
    0,
    3,
    5,
    7
   ]
  },
  "viewer":{
   "jshandler":"webview/handlers/ElementHandler"
  },
  "obj_viewer":[
  ],
  "finder":[
  ]
 },
 {
  "sid":"THEOV:343:257:207#out:1",
  "className":"Simulink.Line",
  "icon":"WebViewIcon5",
  "name":"",
  "label":"",
  "parent":"THEOV:343:257:203",
  "inspector":{
   "params":[
    "SignalNameFromLabel",
    "MustResolveToSignal",
    "ShowPropagatedSignal",
    "DataLogging",
    "TestPoint",
    "SignalObjectPackage",
    "StorageClass",
    "Description",
    "documentLink"
   ],
   "values":[
    "",
    "off",
    "off",
    "off",
    "off",
    "Simulink",
    "Auto",
    "",
    ""
   ],
   "tabs":[
    "Parameter Attributes",
    "Logging and Accessibility",
    "Code Generation",
    "Documentation"
   ],
   "tabs_idx":[
    0,
    3,
    5,
    7
   ]
  },
  "viewer":{
   "jshandler":"webview/handlers/ElementHandler"
  },
  "obj_viewer":[
  ],
  "finder":[
  ]
 },
 {
  "sid":"THEOV:343:257:211#out:1",
  "className":"Simulink.Line",
  "icon":"WebViewIcon5",
  "name":"",
  "label":"",
  "parent":"THEOV:343:257:203",
  "inspector":{
   "params":[
    "SignalNameFromLabel",
    "MustResolveToSignal",
    "ShowPropagatedSignal",
    "DataLogging",
    "TestPoint",
    "SignalObjectPackage",
    "StorageClass",
    "Description",
    "documentLink"
   ],
   "values":[
    "",
    "off",
    "off",
    "off",
    "off",
    "Simulink",
    "Auto",
    "",
    ""
   ],
   "tabs":[
    "Parameter Attributes",
    "Logging and Accessibility",
    "Code Generation",
    "Documentation"
   ],
   "tabs_idx":[
    0,
    3,
    5,
    7
   ]
  },
  "viewer":{
   "jshandler":"webview/handlers/ElementHandler"
  },
  "obj_viewer":[
  ],
  "finder":[
  ]
 },
 {
  "sid":"THEOV:343:257:212#out:2",
  "className":"Simulink.Line",
  "icon":"WebViewIcon5",
  "name":"",
  "label":"",
  "parent":"THEOV:343:257:203",
  "inspector":{
   "params":[
    "SignalNameFromLabel",
    "MustResolveToSignal",
    "ShowPropagatedSignal",
    "DataLogging",
    "TestPoint",
    "SignalObjectPackage",
    "StorageClass",
    "Description",
    "documentLink"
   ],
   "values":[
    "",
    "off",
    "off",
    "off",
    "off",
    "Simulink",
    "Auto",
    "",
    ""
   ],
   "tabs":[
    "Parameter Attributes",
    "Logging and Accessibility",
    "Code Generation",
    "Documentation"
   ],
   "tabs_idx":[
    0,
    3,
    5,
    7
   ]
  },
  "viewer":{
   "jshandler":"webview/handlers/ElementHandler"
  },
  "obj_viewer":[
  ],
  "finder":[
  ]
 },
 {
  "sid":"THEOV:343:257:212#out:1",
  "className":"Simulink.Line",
  "icon":"WebViewIcon5",
  "name":"",
  "label":"",
  "parent":"THEOV:343:257:203",
  "inspector":{
   "params":[
    "SignalNameFromLabel",
    "MustResolveToSignal",
    "ShowPropagatedSignal",
    "DataLogging",
    "TestPoint",
    "SignalObjectPackage",
    "StorageClass",
    "Description",
    "documentLink"
   ],
   "values":[
    "",
    "off",
    "off",
    "off",
    "off",
    "Simulink",
    "Auto",
    "",
    ""
   ],
   "tabs":[
    "Parameter Attributes",
    "Logging and Accessibility",
    "Code Generation",
    "Documentation"
   ],
   "tabs_idx":[
    0,
    3,
    5,
    7
   ]
  },
  "viewer":{
   "jshandler":"webview/handlers/ElementHandler"
  },
  "obj_viewer":[
  ],
  "finder":[
  ]
 },
 {
  "sid":"THEOV:343:257:205#out:1",
  "className":"Simulink.Line",
  "icon":"WebViewIcon5",
  "name":"",
  "label":"",
  "parent":"THEOV:343:257:203",
  "inspector":{
   "params":[
    "SignalNameFromLabel",
    "MustResolveToSignal",
    "ShowPropagatedSignal",
    "DataLogging",
    "TestPoint",
    "SignalObjectPackage",
    "StorageClass",
    "Description",
    "documentLink"
   ],
   "values":[
    "",
    "off",
    "off",
    "off",
    "off",
    "Simulink",
    "Auto",
    "",
    ""
   ],
   "tabs":[
    "Parameter Attributes",
    "Logging and Accessibility",
    "Code Generation",
    "Documentation"
   ],
   "tabs_idx":[
    0,
    3,
    5,
    7
   ]
  },
  "viewer":{
   "jshandler":"webview/handlers/ElementHandler"
  },
  "obj_viewer":[
  ],
  "finder":[
  ]
 },
 {
  "sid":"THEOV:343:257:204#out:1",
  "className":"Simulink.Line",
  "icon":"WebViewIcon5",
  "name":"",
  "label":"",
  "parent":"THEOV:343:257:203",
  "inspector":{
   "params":[
    "SignalNameFromLabel",
    "MustResolveToSignal",
    "ShowPropagatedSignal",
    "DataLogging",
    "TestPoint",
    "SignalObjectPackage",
    "StorageClass",
    "Description",
    "documentLink"
   ],
   "values":[
    "",
    "off",
    "off",
    "off",
    "off",
    "Simulink",
    "Auto",
    "",
    ""
   ],
   "tabs":[
    "Parameter Attributes",
    "Logging and Accessibility",
    "Code Generation",
    "Documentation"
   ],
   "tabs_idx":[
    0,
    3,
    5,
    7
   ]
  },
  "viewer":{
   "jshandler":"webview/handlers/ElementHandler"
  },
  "obj_viewer":[
  ],
  "finder":[
  ]
 }
]